dash_file_cache/__init__.py
dash_file_cache/utilities.py
dash_file_cache/version.py
dash_file_cache/caches/__init__.py
dash_file_cache/caches/abstract.py
dash_file_cache/caches/lrudict.py
dash_file_cache/caches/memory.py
dash_file_cache/caches/tempfile.py
dash_file_cache/caches/typehints.py
dash_file_cache/components/Downloader.py
dash_file_cache/components/PlainDownloader.py
dash_file_cache/components/__init__.py
dash_file_cache/components/_imports_.py
dash_file_cache/components/async-Downloader.js
dash_file_cache/components/async-Downloader.js.map
dash_file_cache/components/async-PlainDownloader.js
dash_file_cache/components/async-PlainDownloader.js.map
dash_file_cache/components/dash_file_cache.min.js
dash_file_cache/components/dash_file_cache.min.js.map
dash_file_cache/components/metadata.json
dash_file_cache/components/package-info.json
dash_file_cache/components/typehints.py
dash_file_cache/services/__init__.py
dash_file_cache/services/data.py
dash_file_cache/services/dfc_mitm.html
dash_file_cache/services/dfc_sw.js
dash_file_cache/services/downloader.py
dash_file_cache/services/reqstream.py
dash_file_cache/services/utilities.py
dash_file_cache-0.2.0.dist-info/licenses/LICENSE
dash_file_cache-0.2.0.dist-info/METADATA
dash_file_cache-0.2.0.dist-info/WHEEL
dash_file_cache-0.2.0.dist-info/top_level.txt
dash_file_cache-0.2.0.dist-info/RECORD
