Metadata-Version: 2.4
Name: dash-file-cache
Version: 0.2.0
Summary: Utilities for providing convenient methods to serve cached data in Plotly-Dash or Flask.
Author-email: Yuchen Jin <cainmagi@gmail.com>
Maintainer-email: Yuchen Jin <cainmagi@gmail.com>
License-Expression: MIT
Project-URL: Homepage, https://github.com/cainmagi/dash-file-cache
Project-URL: Documentation, https://cainmagi.github.io/dash-file-cache/
Project-URL: Repository, https://github.com/cainmagi/dash-file-cache.git
Project-URL: Issues, https://github.com/cainmagi/dash-file-cache/issues
Project-URL: Changelog, https://github.com/cainmagi/dash-file-cache/blob/main/Changelog.md
Keywords: python,python3,python-library,dash,plotly-dash,python-dash,flask,service,cache,cache-service,downloader,file-downloads
Classifier: Development Status :: 3 - Alpha
Classifier: Environment :: Web Environment
Classifier: Intended Audience :: Developers
Classifier: Intended Audience :: Education
Classifier: Intended Audience :: Science/Research
Classifier: Programming Language :: Python :: 3
Classifier: Programming Language :: Python :: 3 :: Only
Classifier: Programming Language :: Python :: 3.8
Classifier: Programming Language :: Python :: 3.9
Classifier: Programming Language :: Python :: 3.10
Classifier: Programming Language :: Python :: 3.11
Classifier: Programming Language :: Python :: 3.12
Classifier: Programming Language :: Python :: 3.13
Classifier: Operating System :: OS Independent
Classifier: Framework :: Dash
Classifier: Framework :: Flask
Classifier: Topic :: Database :: Front-Ends
Requires-Python: >=3.8
License-File: LICENSE
Requires-Dist: dash>=2.7.0
Requires-Dist: flask
Requires-Dist: typing-extensions
Provides-Extra: dev
Requires-Dist: dash[dev,diskcache]>=2.7.0; extra == "dev"
Requires-Dist: build; extra == "dev"
Requires-Dist: wheel; extra == "dev"
Requires-Dist: flake8; extra == "dev"
Requires-Dist: black; extra == "dev"
Provides-Extra: test
Requires-Dist: dash[diskcache,testing]>=2.7.0; extra == "test"
Requires-Dist: multiprocess; extra == "test"
Requires-Dist: werkzeug; extra == "test"
Requires-Dist: chromedriver-binary-auto; extra == "test"
Requires-Dist: pytest; extra == "test"
Requires-Dist: pytest-base-url; extra == "test"
Requires-Dist: pytest-flask>=1.3.0; extra == "test"
Requires-Dist: pytest-html; extra == "test"
Requires-Dist: pytest-metadata; extra == "test"
Requires-Dist: py; extra == "test"
Requires-Dist: pytest-selenium; extra == "test"
Requires-Dist: pytest-variables; extra == "test"
Requires-Dist: pytest-xdist; extra == "test"
Dynamic: license-file
